{"id":393,"ndex":393,"species":"Piplup","form":"Piplup","types":["Water"],"abilities":["Torrent"],"hidden_ability":"Defiant","hp":53,"attack":51,"defense":53,"special_attack":61,"special_defense":56,"speed":40,"total":314,"weight":"11.5 lbs.","height":"1'04\"","class":"Penguin Pokémon","percent_male":0.875,"percent_female":0.125,"egg_groups":["Water 1","Field"],"moves":{"start":["Pound"],"egg":["Double Hit","Supersonic","Yawn","Mud Sport","Mud-Slap","Snore","Flail","Agility","Aqua Ring","Hydro Pump","Feather Dance","Bide","Icy Wind"],"tm":[{"tm_number":"TM01","move":"Work Up"},{"tm_number":"TM06","move":"Toxic"},{"tm_number":"TM07","move":"Hail"},{"tm_number":"TM10","move":"Hidden Power"},{"tm_number":"TM13","move":"Ice Beam"},{"tm_number":"TM14","move":"Blizzard"},{"tm_number":"TM17","move":"Protect"},{"tm_number":"TM18","move":"Rain Dance"},{"tm_number":"TM21","move":"Frustration"},{"tm_number":"TM27","move":"Return"},{"tm_number":"TM31","move":"Brick Break"},{"tm_number":"TM32","move":"Double Team"},{"tm_number":"TM39","move":"Rock Tomb"},{"tm_number":"TM40","move":"Aerial Ace"},{"tm_number":"TM42","move":"Facade"},{"tm_number":"TM44","move":"Rest"},{"tm_number":"TM45","move":"Attract"},{"tm_number":"TM48","move":"Round"},{"tm_number":"TM49","move":"Echoed Voice"},{"tm_number":"TM55","move":"Scald"},{"tm_number":"TM56","move":"Fling"},{"tm_number":"TM60","move":"Quash"},{"tm_number":"TM86","move":"Grass Knot"},{"tm_number":"TM87","move":"Swagger"},{"tm_number":"TM88","move":"Sleep Talk"},{"tm_number":"TM90","move":"Substitute"},{"tm_number":"TM94","move":"Surf"},{"tm_number":"TM98","move":"Waterfall"},{"tm_number":"TM100","move":"Confide"}],"level":[{"level":"4","move":"Growl"},{"level":"8","move":"Bubble"},{"level":"11","move":"Water Sport"},{"level":"15","move":"Peck"},{"level":"18","move":"Bubble Beam"},{"level":"22","move":"Bide"},{"level":"25","move":"Fury Attack"},{"level":"29","move":"Brine"},{"level":"32","move":"Whirlpool"},{"level":"36","move":"Mist"},{"level":"39","move":"Drill Peck"},{"level":"43","move":"Hydro Pump"}],"tutor":["Hydro Cannon"],"oras":["Covet","Signal Beam","Icy Wind","Snore","Water Pulse","Stealth Rock"]},"descriptions":[{"version":"Diamond","description":"Because it is very proud, it hates accepting food from people. Its thick down guards it from cold."},{"version":"Pearl","description":"It lives along shores in northern countries. A skilled swimmer, it dives for over 10 minutes to hunt."},{"version":"Platinum","description":"A poor walker, it often falls down. However, its strong pride makes it puff up its chest without a care."},{"version":"HeartGold/SoulSilver","description":"It doesn’t like to be taken care of. It’s difficult to bond with since it won’t listen to its Trainer."},{"version":"Black/White/Black 2/White 2","description":"A poor walker, it often falls down. However, its strong pride makes it puff up its chest without a care."},{"version":"X/Omega Ruby","description":"It doesn’t like to be taken care of. It’s difficult to bond with since it won’t listen to its Trainer."},{"version":"Y/Alpha Sapphire","description":"Because it is very proud, it hates accepting food from people. Its thick down guards it from cold."}],"family":[{"id":393,"name":"Piplup"},{"id":394,"name":"Prinplup"},{"id":395,"name":"Empoleon"}]}