{"id":267,"ndex":267,"species":"Beautifly","form":"Beautifly","types":["Bug","Flying"],"abilities":["Swarm"],"hidden_ability":"Rivalry","hp":60,"attack":70,"defense":50,"special_attack":100,"special_defense":50,"speed":65,"total":395,"weight":"62.6 lbs.","height":"3'03\"","class":"Butterfly Pokémon","percent_male":0.5,"percent_female":0.5,"egg_groups":["Bug"],"moves":{"start":["Gust"],"egg":[],"tm":[{"tm_number":"TM06","move":"Toxic"},{"tm_number":"TM09","move":"Venoshock"},{"tm_number":"TM10","move":"Hidden Power"},{"tm_number":"TM11","move":"Sunny Day"},{"tm_number":"TM15","move":"Hyper Beam"},{"tm_number":"TM17","move":"Protect"},{"tm_number":"TM19","move":"Roost"},{"tm_number":"TM20","move":"Safeguard"},{"tm_number":"TM21","move":"Frustration"},{"tm_number":"TM22","move":"Solar Beam"},{"tm_number":"TM27","move":"Return"},{"tm_number":"TM29","move":"Psychic"},{"tm_number":"TM30","move":"Shadow Ball"},{"tm_number":"TM32","move":"Double Team"},{"tm_number":"TM40","move":"Aerial Ace"},{"tm_number":"TM42","move":"Facade"},{"tm_number":"TM44","move":"Rest"},{"tm_number":"TM45","move":"Attract"},{"tm_number":"TM46","move":"Thief"},{"tm_number":"TM48","move":"Round"},{"tm_number":"TM53","move":"Energy Ball"},{"tm_number":"TM62","move":"Acrobatics"},{"tm_number":"TM68","move":"Giga Impact"},{"tm_number":"TM83","move":"Infestation"},{"tm_number":"TM87","move":"Swagger"},{"tm_number":"TM88","move":"Sleep Talk"},{"tm_number":"TM89","move":"U-turn"},{"tm_number":"TM90","move":"Substitute"},{"tm_number":"TM100","move":"Confide"}],"level":[{"level":"12","move":"Absorb"},{"level":"15","move":"Stun Spore"},{"level":"17","move":"Morning Sun"},{"level":"20","move":"Air Cutter"},{"level":"22","move":"Mega Drain"},{"level":"25","move":"Silver Wind"},{"level":"27","move":"Attract"},{"level":"30","move":"Whirlwind"},{"level":"32","move":"Giga Drain"},{"level":"35","move":"Bug Buzz"},{"level":"37","move":"Rage"},{"level":"40","move":"Quiver Dance"}],"tutor":[],"oras":["Bug Bite","Signal Beam","Electroweb","Snore","Tailwind","Giga Drain","Air Cutter"]}}